insert_firmware/__init__.py
insert_firmware-1.0.dist-info/METADATA
insert_firmware-1.0.dist-info/WHEEL
insert_firmware-1.0.dist-info/entry_points.txt
insert_firmware-1.0.dist-info/top_level.txt
insert_firmware-1.0.dist-info/RECORD
