Metadata-Version: 2.1
Name: insert-firmware
Version: 1.0
Summary: Add the new firmware into the database
Home-page: UNKNOWN
Author: Omar Diaz
Author-email: diaz@autoaid.de
License: UNKNOWN
Platform: UNKNOWN
Requires-Dist: mysqlclient
